zappix/__init__.py
zappix/agent_active.py
zappix/dstream.py
zappix/get.py
zappix/protocol.py
zappix/sender.py
zappix/server.py
zappix-1.2.3.dist-info/licenses/LICENSE.txt
zappix-1.2.3.dist-info/METADATA
zappix-1.2.3.dist-info/WHEEL
zappix-1.2.3.dist-info/top_level.txt
zappix-1.2.3.dist-info/RECORD
