Metadata-Version: 2.4
Name: zappix
Version: 1.2.3
Summary: A Python replacement for Zabbix sender and get.
Home-page: https://gitlab.com/szuro/zappix
Author: Robert Szulist
Author-email: r.szulist@gmail.com
Keywords: zabbix get sender agent active
Classifier: Development Status :: 5 - Production/Stable
Classifier: Programming Language :: Python :: 3 :: Only
Classifier: Programming Language :: Python :: 3.9
Classifier: Programming Language :: Python :: 3.10
Classifier: Programming Language :: Python :: 3.11
Classifier: Programming Language :: Python :: 3.12
Classifier: Programming Language :: Python :: 3.13
Classifier: Topic :: System :: Monitoring
Classifier: License :: OSI Approved :: MIT License
License-File: LICENSE.txt
Requires-Dist: pyOpenSSL
Requires-Dist: pyopenssl-psk
Provides-Extra: dev
Requires-Dist: tox; extra == "dev"
Requires-Dist: pyzabbix; extra == "dev"
Dynamic: author
Dynamic: author-email
Dynamic: classifier
Dynamic: description
Dynamic: description-content-type
Dynamic: home-page
Dynamic: keywords
Dynamic: license-file
Dynamic: provides-extra
Dynamic: requires-dist
Dynamic: summary
